{
    "sourceFile": "style.css",
    "activeCommit": 0,
    "commits": [
        {
            "activePatchIndex": 2,
            "patches": [
                {
                    "date": 1709739917617,
                    "content": "Index: \n===================================================================\n--- \n+++ \n"
                },
                {
                    "date": 1709740267346,
                    "content": "Index: \n===================================================================\n--- \n+++ \n@@ -27,10 +27,19 @@\n \r\n .upper-btn-box .left-box {\r\n   width: 50%;\r\n   height: 100%;\r\n+}\r\n \r\n-\r\n+.upper-btn-box .left-box button{\r\n+  border: none;\r\n+  outline: none;\r\n+  background-color: #4286F5;\r\n+  padding: 13px;\r\n+  font-size: 22px;\r\n+  font-family: Verdana;\r\n+  color: #fff;\r\n+  margin: 0px 10px;\r\n }\r\n \r\n .upper-btn-box .right-box {\r\n   width: 50%;\r\n"
                },
                {
                    "date": 1709740561535,
                    "content": "Index: \n===================================================================\n--- \n+++ \n@@ -43,6 +43,10 @@\n \r\n .upper-btn-box .right-box {\r\n   width: 50%;\r\n   height: 100%;\r\n-  background-color: rgb(47, 38, 171);\r\n+  \r\n+}\r\n+.upper-btn-box .right-box i{\r\n+  font-size: 25px ;\r\n+  color: #4286F5;\r\n }\n\\ No newline at end of file\n"
                }
            ],
            "date": 1709739917617,
            "name": "Commit-0",
            "content": "* {\r\n  padding: 0;\r\n  margin: 0;\r\n  box-sizing: border-box;\r\n}\r\n\r\n.header {\r\n  width: 100%;\r\n  padding: 10px 30px;\r\n  background-color: #ee534f;\r\n}\r\n\r\n.header h5 {\r\n  font-weight: bold;\r\n  font-family: verdana;\r\n  font-size: 28px;\r\n  color: #fff;\r\n}\r\n\r\n/* upper btn box */\r\n.upper-btn-box {\r\n  width: 100%;\r\n  height: 100px;\r\n  display: flex;\r\n  padding: 30px;\r\n}\r\n\r\n.upper-btn-box .left-box {\r\n  width: 50%;\r\n  height: 100%;\r\n  \r\n\r\n}\r\n\r\n.upper-btn-box .right-box {\r\n  width: 50%;\r\n  height: 100%;\r\n  background-color: rgb(47, 38, 171);\r\n}"
        }
    ]
}